fmfancy/__init__.py
fmfancy/database.py
fmfancy/events.py
fmfancy/models.py
fmfancy/permissions.py
fmfancy/startup_shutdown.py
fmfancy/utils.py
fmfancy-0.0.4.dist-info/LICENSE
fmfancy-0.0.4.dist-info/METADATA
fmfancy-0.0.4.dist-info/WHEEL
fmfancy-0.0.4.dist-info/top_level.txt
fmfancy-0.0.4.dist-info/RECORD
