Metadata-Version: 2.1
Name: fmfancy
Version: 0.0.4
Summary: Test_pkg
Home-page: UNKNOWN
Author: Tobiasz Gleba
Author-email: tobiasz.gleba24@gmail.com
License: UNKNOWN
Keywords: python,fastapi,workflow
Platform: UNKNOWN
Classifier: Development Status :: 1 - Planning
Classifier: Intended Audience :: Developers
Classifier: License :: OSI Approved :: MIT License
Classifier: Programming Language :: Python :: 3
Classifier: Operating System :: OS Independent
Requires-Python: >=3.6
License-File: LICENSE
Requires-Dist: fastapi
Requires-Dist: motor
